altinkaynak/__init__.py
altinkaynak-0.0.2.dist-info/METADATA
altinkaynak-0.0.2.dist-info/WHEEL
altinkaynak-0.0.2.dist-info/licenses/LICENSE
altinkaynak-0.0.2.dist-info/RECORD
