Metadata-Version: 2.1
Name: altinkaynak
Version: 0.0.2
Summary: Get currency rates from the source altinkaynak.com
Project-URL: Homepage, https://github.com/mustafa-mercanli/altinkaynak
Author-email: Mustafa MERCANLI <mustafa.mercanli@gmail.com>
License: Copyright (c) 2018 The Python Packaging Authority
Classifier: License :: OSI Approved :: MIT License
Classifier: Operating System :: OS Independent
Classifier: Programming Language :: Python :: 3
Requires-Python: >=3.0
